[
  {"query": "niike магазин", "attributes": {"BRANDS": ["nike"]}},
  {"query": "рост 164", "attributes": {"CLOTHING_KIDS_GROTH": ["164"]}},
  {"query": "в цвете оранжевый", "attributes": {"COLORS": ["оранжевый"]}},
  {"query": "Детская обувь 23", "attributes": {"SHOE_SIZES_KIDS": ["23"]}},
  {"query": "размер обуви 44", "attributes": {"SHOE_SIZES_ADULT": ["44"]}},
  {"query": "56 размер", "attributes": {"CLOTHING_SIZES_NUMERIC": ["56"]}},
  {"query": "арт 12345 заказ", "attributes": {}},
  {"query": "30см размер", "attributes": {"LINEAR_DIMS_CM_MM": ["30см"]}},
  {"query": "ботинки 32 детские", "attributes": {"SHOE_SIZES_KIDS": ["32"]}},
  {"query": "быстрая доставка акция", "attributes": {}},
  {"query": "abc товар", "attributes": {}},
  {"query": "Память 64гб рам", "attributes": {"ELECTRONICS_MEMORY": ["64гб рам"]}},
  {"query": "50 размер размер 70х70см вельвет купить сумка", "attributes": {"CLOTHING_SIZES_NUMERIC": ["50"], "TEXTILE_DIMS": ["70х70см"], "CATEGORIES": ["сумка"], "MATERIALS": ["вельвет"]}},
  {"query": "рост 86", "attributes": {"CLOTHING_KIDS_GROTH": ["86"]}},
  {"query": "ГАБАРИТЫ 10СМ", "attributes": {"LINEAR_DIMS_CM_MM": ["10см"]}},
  {"query": "обувь 39 размер XXXL купить", "attributes": {"SHOE_SIZES_ADULT": ["39"], "CLOTHING_SIZES_LETTER": ["XXXL"], "MATERIALS": ["кожа"]}},
  {"query": "25 р-р ноги детский", "attributes": {"SHOE_SIZES_KIDS": ["25"]}},
  {"query": "nike вес 2кг 1м", "attributes": {"LINEAR_DIMS_CM_MM": ["1м"], "BRANDS": ["nike"], "WEIGHT": ["2кг"]}},
  {"query": "джинсы regular", "attributes": {"CLOTHING_FIT": ["regular"]}},
  {"query": "ноутбук 256гб", "attributes": {"ELECTRONICS_MEMORY": ["256гб"]}},
  {"query": "контейнер 2л", "attributes": {"VOLUME": ["2л"]}},
  {"query": "рост 158 1м коричневый вес 250г", "attributes": {"WEIGHT": ["250г"], "COLORS": ["коричневый"], "CLOTHING_KIDS_GROTH": ["158"], "LINEAR_DIMS_CM_MM": ["1м"]}},
  {"query": "килограмм товар", "attributes": {"WEIGHT": ["10кг"]}},
  {"query": "плед 50х50см", "attributes": {"TEXTILE_DIMS": ["50х50см"]}},
  {"query": "рост 134", "attributes": {"CLOTHING_KIDS_GROTH": ["134"]}},
  {"query": "test123 товар", "attributes": {}},
  {"query": "Размер обуви 41", "attributes": {"SHOE_SIZES_ADULT": ["41"]}},
  {"query": "габариты 10мм", "attributes": {"LINEAR_DIMS_CM_MM": ["10мм"]}},
  {"query": "телевизор 6.7", "attributes": {"SCREEN_DIAGONALS": ["6.7"]}},
  {"query": "РАЗМЕР 70Х70СМ", "attributes": {"TEXTILE_DIMS": ["70х70см"]}},
  {"query": "test123 цена", "attributes": {}},
  {"query": "CALVIN KLEIN РАСПРОДАЖА", "attributes": {"BRANDS": ["calvin klein"]}},
  {"query": "детский 5мм regular", "attributes": {"LINEAR_DIMS_CM_MM": ["5мм"], "CLOTHING_FIT": ["regular"]}},
  {"query": "контейнер 500мл", "attributes": {"VOLUME": ["500мл"]}},
  {"query": "samsung оригинал", "attributes": {"BRANDS": ["samsung"]}},
  {"query": "купить разммер XXXL", "attributes": {"SHOE_SIZES_ADULT": ["47"], "TEXTILE_DIMS": ["50х50см"], "CLOTHING_SIZES_LETTER": ["XXXL"]}},
  {"query": "сант р-р", "attributes": {"LINEAR_DIMS_CM_MM": ["15см"]}},
  {"query": "объем 500мл", "attributes": {"VOLUME": ["500мл"]}},
  {"query": "код товара 555 акция", "attributes": {}},
  {"query": "ВЕС 500Г", "attributes": {"WEIGHT": ["500г"]}},
  {"query": "просто товар купить", "attributes": {}},
  {"query": "атлас материал", "attributes": {"MATERIALS": ["атлас"]}},
  {"query": "смартфон 4гб", "attributes": {"ELECTRONICS_MEMORY": ["4гб"]}},
  {"query": "детская обувь 33 распродажа размер S", "attributes": {"CLOTHING_SIZES_LETTER": ["S"], "SHOE_SIZES_KIDS": ["33"]}},
  {"query": "id 789012 заказ", "attributes": {}},
  {"query": "хит цена", "attributes": {}},
  {"query": "мышка объем 50мл детский рост 122 вес 100г", "attributes": {"CATEGORIES": ["мышка"], "VOLUME": ["50мл"], "WEIGHT": ["100г"], "CLOTHING_KIDS_GROTH": ["122"]}},
  {"query": "фирменный asus", "attributes": {"BRANDS": ["asus"]}},
  {"query": "46 размер ноги", "attributes": {"SHOE_SIZES_ADULT": ["46"]}},
  {"query": "объем 10л", "attributes": {"VOLUME": ["10л"]}},
  {"query": "5кг товар", "attributes": {"WEIGHT": ["5кг"]}},
  {"query": "оригинал рост 128 коврик р-р XS сантиметр", "attributes": {"CLOTHING_KIDS_GROTH": ["128"], "LINEAR_DIMS_CM_MM": ["50см"], "CLOTHING_SIZES_LETTER": ["XS"], "CATEGORIES": ["коврик"]}},
  {"query": "атлас оригинал кофта детская обувь 30", "attributes": {"SHOE_SIZES_KIDS": ["30"], "CATEGORIES": ["кофта"], "MATERIALS": ["атлас"]}},
  {"query": "распродажа цена", "attributes": {}},
  {"query": "4гб новинка размер 200х200см", "attributes": {"ELECTRONICS_MEMORY": ["4гб"], "TEXTILE_DIMS": ["200х220см"]}},
  {"query": "РАЗМЕР 46", "attributes": {"CLOTHING_SIZES_NUMERIC": ["46"]}},
  {"query": "ВЕС 1.5КГ", "attributes": {"WEIGHT": ["1.5кг"]}},
  {"query": "8гб распродажа объем 5л", "attributes": {"VOLUME": ["5л"], "ELECTRONICS_MEMORY": ["8гб"]}},
  {"query": "1л емкость", "attributes": {"VOLUME": ["1л"]}},
  {"query": "nikе распродажа", "attributes": {"BRANDS": ["nike"]}},
  {"query": "размер XS свободный", "attributes": {"CLOTHING_FIT": ["свободный"], "CLOTHING_SIZES_LETTER": ["XS"]}},
  {"query": "детская одежда мужская", "attributes": {"CATEGORIES": ["детская одежда"]}},
  {"query": "детская обувь 32", "attributes": {"SHOE_SIZES_KIDS": ["32"]}},
  {"query": "XS р-р", "attributes": {"CLOTHING_SIZES_LETTER": ["XS"]}},
  {"query": "заказ цена", "attributes": {}},
  {"query": "детская обувь 23 свитер оригинал", "attributes": {"CATEGORIES": ["свитер"], "SHOE_SIZES_KIDS": ["23"], "VOLUME": ["500мл"], "CLOTHING_FIT": ["приталенный"]}},
  {"query": "КОНТЕЙНЕР 250МЛ", "attributes": {"VOLUME": ["250мл"]}},
  {"query": "under armour новинка размер L", "attributes": {"CLOTHING_SIZES_LETTER": ["L"], "BRANDS": ["under armour"]}},
  {"query": "габариты 40см", "attributes": {"LINEAR_DIMS_CM_MM": ["40см"]}},
  {"query": "выбрать 52", "attributes": {"CLOTHING_SIZES_NUMERIC": ["52"]}},
  {"query": "детское 62", "attributes": {"CLOTHING_KIDS_GROTH": ["62"]}},
  {"query": "планшет ikea детская обувь 34 оригинал", "attributes": {"CATEGORIES": ["планшет"], "BRANDS": ["ikea"], "SHOE_SIZES_KIDS": ["34"]}},
  {"query": "test акция", "attributes": {}},
  {"query": "ДЖИНСЫ ШИРОКИЙ", "attributes": {"CLOTHING_FIT": ["широкий"]}},
  {"query": "прямой купить", "attributes": {"CLOTHING_FIT": ["прямой"], "WEIGHT": ["2кг"], "VOLUME": ["250мл"]}},
  {"query": "продукт 10кг", "attributes": {"WEIGHT": ["10кг"]}},
  {"query": "фирменный huawei", "attributes": {"BRANDS": ["huawei"]}},
  {"query": "память 2тб", "attributes": {"ELECTRONICS_MEMORY": ["2тб"]}},
  {"query": "Товар оранжевый", "attributes": {"COLORS": ["оранжевый"]}},
  {"query": "упаковка 750г", "attributes": {"WEIGHT": ["750г"]}},
  {"query": "фасон широкий", "attributes": {"CLOTHING_FIT": ["широкий"]}},
  {"query": "женский размер XS converse", "attributes": {"SHOE_SIZES_KIDS": ["25"], "BRANDS": ["converse"], "CLOTHING_SIZES_LETTER": ["XS"], "ELECTRONICS_MEMORY": ["64гб рам"]}},
  {"query": "обувь 41 детская обувь 24 женский объем 2л", "attributes": {"VOLUME": ["2л"], "SHOE_SIZES_ADULT": ["41"], "SHOE_SIZES_KIDS": ["24"]}},
  {"query": "детский мышка 48 размер", "attributes": {"CLOTHING_SIZES_NUMERIC": ["48"], "CATEGORIES": ["мышка"]}},
  {"query": "диагональ 13дюймов", "attributes": {"SCREEN_DIAGONALS": ["13дюймов"]}},
  {"query": "монитор 17дюймов", "attributes": {"SCREEN_DIAGONALS": ["17дюймов"]}},
  {"query": "размер 70х70см 32гб объем 500мл оригинал", "attributes": {"ELECTRONICS_MEMORY": ["32гб"], "VOLUME": ["500мл"], "TEXTILE_DIMS": ["70х70см"]}},
  {"query": "распродажа 32гб", "attributes": {"LINEAR_DIMS_CM_MM": ["10см"], "BRANDS": ["the north face"], "ELECTRONICS_MEMORY": ["32гб"], "TEXTILE_DIMS": ["100х150см"]}},
  {"query": "рост 62 коврик детская обувь 20 объем 250мл", "attributes": {"SHOE_SIZES_KIDS": ["20"], "VOLUME": ["250мл"], "CLOTHING_KIDS_GROTH": ["62"], "CATEGORIES": ["коврик"]}},
  {"query": "размер 42", "attributes": {"CLOTHING_SIZES_NUMERIC": ["42"]}},
  {"query": "обувь 40", "attributes": {"SHOE_SIZES_ADULT": ["40"]}},
  {"query": "ноутбук gb", "attributes": {"ELECTRONICS_MEMORY": ["8гб"]}},
  {"query": "Товар 5мм", "attributes": {"LINEAR_DIMS_CM_MM": ["5мм"]}},
  {"query": "Джинсы узкий", "attributes": {"CLOTHING_FIT": ["узкий"]}},
  {"query": "1л емкость", "attributes": {"VOLUME": ["1л"]}},
  {"query": "размер 24 ребенок", "attributes": {"SHOE_SIZES_KIDS": ["24"]}},
  {"query": "код товара 555", "attributes": {}},
  {"query": "111 купить", "attributes": {}},
  {"query": "футболка детская", "attributes": {"CATEGORIES": ["футболка"]}},
  {"query": "купить 54 размер объем 250мл", "attributes": {"CLOTHING_SIZES_NUMERIC": ["54"], "VOLUME": ["250мл"]}},
  {"query": "samsung размер 70х70см", "attributes": {"BRANDS": ["samsung"], "SCREEN_DIAGONALS": ["13дюймов"], "TEXTILE_DIMS": ["70х70см"], "MATERIALS": ["шерсть"]}},
  {"query": "sku 98765 купить", "attributes": {}},
  {"query": "детская обувь 33 бархат вес 750г", "attributes": {"SHOE_SIZES_KIDS": ["33"], "WEIGHT": ["750г"], "MATERIALS": ["бархат"]}},
  {"query": "коврик размер XL", "attributes": {"CLOTHING_SIZES_LETTER": ["XL"], "TEXTILE_DIMS": ["50х50см"], "ELECTRONICS_MEMORY": ["256гб"], "CATEGORIES": ["коврик"]}},
  {"query": "полотенце samsung", "attributes": {"VOLUME": ["250мл"], "CLOTHING_FIT": ["loose"], "CATEGORIES": ["полотенце"], "BRANDS": ["samsung"]}},
  {"query": "46 размер", "attributes": {"CLOTHING_SIZES_NUMERIC": ["46"]}},
  {"query": "бархат размер S columbia вес 100г", "attributes": {"WEIGHT": ["100г"], "CLOTHING_SIZES_LETTER": ["S"], "MATERIALS": ["бархат"], "BRANDS": ["columbia"]}},
  {"query": "фирменный берберри", "attributes": {"BRANDS": ["берберри"]}},
  {"query": "48 размер мужской 4гб", "attributes": {"CLOTHING_SIZES_NUMERIC": ["48"], "ELECTRONICS_MEMORY": ["4гб"]}},
  {"query": "Джинсы regular", "attributes": {"CLOTHING_FIT": ["regular"]}},
  {"query": "100г товар", "attributes": {"WEIGHT": ["100г"]}},
  {"query": "серый оттенок", "attributes": {"COLORS": ["серый"]}},
  {"query": "размер обуви 45", "attributes": {"SHOE_SIZES_ADULT": ["45"]}},
  {"query": "разммер 160х200см", "attributes": {"TEXTILE_DIMS": ["160х200см"]}},
  {"query": "экран 40дюймов распродажа объем 5л", "attributes": {"SCREEN_DIAGONALS": ["40дюймов"], "VOLUME": ["5л"]}},
  {"query": "новинка вес 500г 32гб объем 750мл экран 13дюймов", "attributes": {"ELECTRONICS_MEMORY": ["32гб"], "WEIGHT": ["500г"], "VOLUME": ["750мл"], "SCREEN_DIAGONALS": ["13дюймов"]}},
  {"query": "ФУТБОЛКА XS", "attributes": {"CLOTHING_SIZES_LETTER": ["XS"]}},
  {"query": "хит цена", "attributes": {}},
  {"query": "одежда на рост 140", "attributes": {"CLOTHING_KIDS_GROTH": ["140"]}},
  {"query": "лен материал", "attributes": {"MATERIALS": ["лен"]}},
  {"query": "купить хлопок размер 200х200см", "attributes": {"TEXTILE_DIMS": ["200х200см"], "MATERIALS": ["хлопок"]}},
  {"query": "товар салатовый", "attributes": {"COLORS": ["салатовый"]}},
  {"query": "8гб рост 146 распродажа", "attributes": {"CLOTHING_KIDS_GROTH": ["146"], "ELECTRONICS_MEMORY": ["8гб"]}},
  {"query": "длина 5мм", "attributes": {"LINEAR_DIMS_CM_MM": ["5мм"]}},
  {"query": "кожа ткань", "attributes": {"MATERIALS": ["кожа"]}},
  {"query": "Монитор 6.1", "attributes": {"SCREEN_DIAGONALS": ["6.1"]}},
  {"query": "xxx акция", "attributes": {}},
  {"query": "размер XXXL объем 2л новинка", "attributes": {"SHOE_SIZES_KIDS": ["22"], "CLOTHING_SIZES_LETTER": ["XXXL"], "VOLUME": ["2л"]}},
  {"query": "диор новинка", "attributes": {"SCREEN_DIAGONALS": ["27дюймов"], "WEIGHT": ["500г"], "BRANDS": ["диор"]}},
  {"query": "футболка xxxl", "attributes": {"CLOTHING_SIZES_LETTER": ["XXXL"]}},
  {"query": "память 32гб", "attributes": {"ELECTRONICS_MEMORY": ["32гб"]}},
  {"query": "новинка цена", "attributes": {}},
  {"query": "одежда 40", "attributes": {"CLOTHING_SIZES_NUMERIC": ["40"]}},
  {"query": "женский зауженный размер 200х200см вес 10кг рост 140", "attributes": {"CLOTHING_FIT": ["зауженный"], "CLOTHING_KIDS_GROTH": ["140"], "WEIGHT": ["10кг"], "TEXTILE_DIMS": ["200х200см"]}},
  {"query": "кеды женская", "attributes": {"CATEGORIES": ["кеды"]}},
  {"query": "купить размер 140х200см объем 10л", "attributes": {"TEXTILE_DIMS": ["140х200см"], "CLOTHING_SIZES_LETTER": ["XS"], "VOLUME": ["10л"]}},
  {"query": "купить экран 27дюймов куртка 42 размер", "attributes": {"CATEGORIES": ["куртка"], "CLOTHING_SIZES_NUMERIC": ["42"], "SCREEN_DIAGONALS": ["27дюймов"]}},
  {"query": "кроссовки 42", "attributes": {"SHOE_SIZES_ADULT": ["42"]}},
  {"query": "товар 1м", "attributes": {"LINEAR_DIMS_CM_MM": ["1м"]}},
  {"query": "huawei магазин", "attributes": {"BRANDS": ["huawei"]}},
  {"query": "gucci детская обувь 27 детский", "attributes": {"SHOE_SIZES_KIDS": ["27"], "BRANDS": ["gucci"]}},
  {"query": "детская обувь 35 объем 2л новинка узкий", "attributes": {"SHOE_SIZES_KIDS": ["35"], "CLOTHING_FIT": ["узкий"], "VOLUME": ["2л"]}},
  {"query": "товар бордовый", "attributes": {"COLORS": ["бордовый"]}},
  {"query": "КОНТЕЙНЕР 10Л", "attributes": {"VOLUME": ["10л"]}},
  {"query": "fila оригинал", "attributes": {"BRANDS": ["fila"]}},
  {"query": "клавиатура экран 15.6", "attributes": {"SCREEN_DIAGONALS": ["15.6"], "CATEGORIES": ["клавиатура"]}},
  {"query": "экран 15.6 купить asus", "attributes": {"BRANDS": ["asus"], "SCREEN_DIAGONALS": ["15.6"]}},
  {"query": "Кожа материал", "attributes": {"MATERIALS": ["кожа"]}},
  {"query": "обувь 43 2м", "attributes": {"BRANDS": ["hp"], "LINEAR_DIMS_CM_MM": ["2м"], "SHOE_SIZES_ADULT": ["43"]}},
  {"query": "детская обувь 22 новинка", "attributes": {"MATERIALS": ["мембрана"], "SHOE_SIZES_KIDS": ["22"]}},
  {"query": "р-р обуви 47", "attributes": {"SHOE_SIZES_ADULT": ["47"]}},
  {"query": "42 размер мужской черный обувь 41", "attributes": {"COLORS": ["черный"], "SHOE_SIZES_ADULT": ["41"], "CLOTHING_SIZES_NUMERIC": ["42"]}},
  {"query": "смартфон 64гб рам", "attributes": {"ELECTRONICS_MEMORY": ["64гб рам"]}},
  {"query": "в цвете лиловый", "attributes": {"COLORS": ["лиловый"]}},
  {"query": "дюйм цвете синии", "attributes": {"COLORS": ["синий"]}},
  {"query": "бархат материал", "attributes": {"MATERIALS": ["бархат"]}},
  {"query": "купить коричневый экран 40дюймов", "attributes": {"SCREEN_DIAGONALS": ["40дюймов"], "COLORS": ["коричневый"]}},
  {"query": "sony оригинал", "attributes": {"BRANDS": ["sony"]}},
  {"query": "вискоза ткань", "attributes": {"MATERIALS": ["вискоза"]}},
  {"query": "Товар мультиколор", "attributes": {"COLORS": ["мультиколор"]}},
  {"query": "объем 3л вес 1.5кг", "attributes": {"VOLUME": ["3л"], "WEIGHT": ["1.5кг"]}},
  {"query": "смартфон 512гб", "attributes": {"ELECTRONICS_MEMORY": ["512гб"]}},
  {"query": "размер 180х200см эластан", "attributes": {"MATERIALS": ["эластан"], "TEXTILE_DIMS": ["180х200см"]}},
  {"query": "asdfgh акция", "attributes": {}},
  {"query": "серый купить обувь 43", "attributes": {"SHOE_SIZES_ADULT": ["43"], "COLORS": ["серый"]}},
  {"query": "111 товар", "attributes": {}},
  {"query": "Одежда на рост 140", "attributes": {"CLOTHING_KIDS_GROTH": ["140"]}},
  {"query": "28 размер ноги детский", "attributes": {"SHOE_SIZES_KIDS": ["28"]}},
  {"query": "обувь 42 размер см женский разммер приталеный", "attributes": {"SHOE_SIZES_ADULT": ["42"], "TEXTILE_DIMS": ["70х70см"], "SCREEN_DIAGONALS": ["50дюймов"], "CLOTHING_SIZES_LETTER": ["M"]}},
  {"query": "размер сантиметр", "attributes": {"TEXTILE_DIMS": ["240х260см"]}},
  {"query": "постельное 50х50см", "attributes": {"TEXTILE_DIMS": ["50х50см"]}},
  {"query": "ноутбук 512гб", "attributes": {"ELECTRONICS_MEMORY": ["512гб"]}},
  {"query": "id 789012", "attributes": {}},
  {"query": "товар зеленый", "attributes": {"COLORS": ["зеленый"]}},
  {"query": "размер 180х200см рост 116 детская обувь 30 экран", "attributes": {"SCREEN_DIAGONALS": ["32дюйма"], "SHOE_SIZES_KIDS": ["30"], "CLOTHING_KIDS_GROTH": ["116"], "TEXTILE_DIMS": ["180х200см"]}},
  {"query": "размер L", "attributes": {"CLOTHING_SIZES_LETTER": ["L"]}},
  {"query": "обувь 43 купить", "attributes": {"SHOE_SIZES_ADULT": ["43"], "VOLUME": ["50мл"], "WEIGHT": ["500г"], "SHOE_SIZES_KIDS": ["24"]}},
  {"query": "puma 100см рост 110 детская обувь 27", "attributes": {"CLOTHING_KIDS_GROTH": ["110"], "LINEAR_DIMS_CM_MM": ["100см"], "BRANDS": ["puma"], "SHOE_SIZES_KIDS": ["27"]}},
  {"query": "50СМ РАЗМЕР", "attributes": {"LINEAR_DIMS_CM_MM": ["50см"]}},
  {"query": "рост 104 1м женский", "attributes": {"LINEAR_DIMS_CM_MM": ["1м"], "CLOTHING_KIDS_GROTH": ["104"]}},
  {"query": "Мультиколор оттенок", "attributes": {"COLORS": ["мультиколор"]}},
  {"query": "asics купить размер XL рост 128", "attributes": {"CLOTHING_FIT": ["широкий"], "CLOTHING_SIZES_LETTER": ["XL"], "BRANDS": ["asics"], "CLOTHING_KIDS_GROTH": ["128"]}},
  {"query": "обувь 38 куртка xiaomi узкий детский", "attributes": {"SHOE_SIZES_ADULT": ["38"], "CATEGORIES": ["куртка"], "CLOTHING_FIT": ["узкий"], "BRANDS": ["xiaomi"]}},
  {"query": "зарядка zara", "attributes": {"BRANDS": ["zara"], "CATEGORIES": ["зарядка"], "CLOTHING_SIZES_LETTER": ["M"]}},
  {"query": "Футболка m", "attributes": {"CLOTHING_SIZES_LETTER": ["M"]}},
  {"query": "hm объем 1л женский", "attributes": {"VOLUME": ["1л"], "BRANDS": ["hm"]}},
  {"query": "детская обувь 20 100см", "attributes": {"SCREEN_DIAGONALS": ["6.1"], "SHOE_SIZES_KIDS": ["20"], "CLOTHING_SIZES_LETTER": ["XXL"], "LINEAR_DIMS_CM_MM": ["100см"]}},
  {"query": "16гб эко кожа оригинал вес 1.5кг", "attributes": {"MATERIALS": ["эко кожа"], "WEIGHT": ["1.5кг"], "ELECTRONICS_MEMORY": ["16гб"]}},
  {"query": "одежда 44", "attributes": {"CLOTHING_SIZES_NUMERIC": ["44"]}},
  {"query": "asics магазин", "attributes": {"BRANDS": ["asics"]}},
  {"query": "арт 12345 товар", "attributes": {}},
  {"query": "код товара 555 цена", "attributes": {}},
  {"query": "код 445566 товар", "attributes": {}},
  {"query": "рост 164 лен", "attributes": {"CATEGORIES": ["подушка"], "CLOTHING_KIDS_GROTH": ["164"], "MATERIALS": ["лен"], "CLOTHING_SIZES_LETTER": ["XXL"]}},
  {"query": "размер M tommy hilfiger", "attributes": {"CLOTHING_SIZES_LETTER": ["M"], "BRANDS": ["tommy hilfiger"], "COLORS": ["золотой"]}},
  {"query": "купить платье", "attributes": {"CATEGORIES": ["платье"]}},
  {"query": "плед см", "attributes": {"TEXTILE_DIMS": ["100х150см"]}},
  {"query": "asdfgh товар", "attributes": {}},
  {"query": "женский экран 15.6 zara детская обувь 21", "attributes": {"BRANDS": ["zara"], "SHOE_SIZES_KIDS": ["21"], "SCREEN_DIAGONALS": ["15.6"]}},
  {"query": "размер 100х150см", "attributes": {"TEXTILE_DIMS": ["100х150см"]}},
  {"query": "111 товар", "attributes": {}},
  {"query": "лиловый оттенок", "attributes": {"COLORS": ["лиловый"]}},
  {"query": "asdfgh акция", "attributes": {}},
  {"query": "40см экран 13дюймов мужской", "attributes": {"SCREEN_DIAGONALS": ["13дюймов"], "LINEAR_DIMS_CM_MM": ["40см"]}},
  {"query": "сантиметр gb", "attributes": {"ELECTRONICS_MEMORY": ["4гб"]}},
  {"query": "оригинал обувь 44", "attributes": {"SHOE_SIZES_ADULT": ["44"], "MATERIALS": ["бархат"]}},
  {"query": "эко кожа ткань", "attributes": {"MATERIALS": ["эко кожа"]}},
  {"query": "объем 250мл", "attributes": {"VOLUME": ["250мл"]}},
  {"query": "телевизор 6.1", "attributes": {"SCREEN_DIAGONALS": ["6.1"]}},
  {"query": "размер обуви 38", "attributes": {"SHOE_SIZES_ADULT": ["38"]}},
  {"query": "вискоза 40см новинка hm вес 1.5кг", "attributes": {"MATERIALS": ["вискоза"], "BRANDS": ["hm"], "LINEAR_DIMS_CM_MM": ["40см"], "WEIGHT": ["1.5кг"]}},
  {"query": "детская обувь 22 48 размер размер 100х150см", "attributes": {"TEXTILE_DIMS": ["100х150см"], "SHOE_SIZES_KIDS": ["22"], "CLOTHING_SIZES_NUMERIC": ["48"], "CLOTHING_SIZES_LETTER": ["S"]}},
  {"query": "ОБЪЕМ 500МЛ", "attributes": {"VOLUME": ["500мл"]}},
  {"query": "ПЛЕД 70Х70СМ", "attributes": {"TEXTILE_DIMS": ["70х70см"]}},
  {"query": "одежда вискоза", "attributes": {"MATERIALS": ["вискоза"]}},
  {"query": "вес 250г экран дюймов детский", "attributes": {"WEIGHT": ["250г"], "SCREEN_DIAGONALS": ["13дюймов"], "CLOTHING_FIT": ["приталенный"]}},
  {"query": "рост 92 размер адидаз обувь 42", "attributes": {"SHOE_SIZES_ADULT": ["42"], "CLOTHING_SIZES_LETTER": ["S"], "CLOTHING_FIT": ["классический"], "CLOTHING_KIDS_GROTH": ["92"]}},
  {"query": "Мятный оттенок", "attributes": {"COLORS": ["мятный"]}},
  {"query": "экран 13дюймов разммер 180х200см", "attributes": {"TEXTILE_DIMS": ["180х200см"], "WEIGHT": ["250г"], "SCREEN_DIAGONALS": ["13дюймов"], "LINEAR_DIMS_CM_MM": ["5мм"]}},
  {"query": "размер 180х200см детская обувь 25", "attributes": {"TEXTILE_DIMS": ["180х200см"], "BRANDS": ["nike"], "SHOE_SIZES_KIDS": ["25"], "WEIGHT": ["10кг"]}},
  {"query": "из атлас", "attributes": {"MATERIALS": ["атлас"]}},
  {"query": "размер 150х200см вискоза вес 1кг монитор", "attributes": {"TEXTILE_DIMS": ["150х200см"], "MATERIALS": ["вискоза"], "WEIGHT": ["1кг"], "CATEGORIES": ["монитор"]}},
  {"query": "объем 2л новинка 58 р-р детская одежда", "attributes": {"CLOTHING_SIZES_NUMERIC": ["58"], "VOLUME": ["2л"], "CATEGORIES": ["детская одежда"]}},
  {"query": "loose оригинал размер 50х50см 56 размер new balance", "attributes": {"CLOTHING_SIZES_NUMERIC": ["56"], "BRANDS": ["new balance"], "CLOTHING_FIT": ["loose"], "TEXTILE_DIMS": ["50х50см"]}},
  {"query": "ПОСТЕЛЬНОЕ 160Х200СМ", "attributes": {"TEXTILE_DIMS": ["160х200см"]}},
  {"query": "продукт 100г", "attributes": {"WEIGHT": ["100г"]}},
  {"query": "фасон классический", "attributes": {"CLOTHING_FIT": ["классический"]}},
  {"query": "салатовый часы размер L детская обувь 21", "attributes": {"SHOE_SIZES_KIDS": ["21"], "CATEGORIES": ["часы"], "COLORS": ["салатовый"], "CLOTHING_SIZES_LETTER": ["L"]}},
  {"query": "ДЕТСКАЯ ОБУВЬ 21", "attributes": {"SHOE_SIZES_KIDS": ["21"]}},
  {"query": "из искусственная кожа", "attributes": {"MATERIALS": ["искусственная кожа"]}},
  {"query": "номер 778899 акция", "attributes": {}},
  {"query": "детский 25см", "attributes": {"CLOTHING_KIDS_GROTH": ["68"], "LINEAR_DIMS_CM_MM": ["25см"], "VOLUME": ["1л"], "MATERIALS": ["шелк"]}},
  {"query": "одежда XS", "attributes": {"CLOTHING_SIZES_LETTER": ["XS"]}},
  {"query": "монитор детская", "attributes": {"CATEGORIES": ["монитор"]}},
  {"query": "128гб прозрачный", "attributes": {"ELECTRONICS_MEMORY": ["128гб"], "CLOTHING_KIDS_GROTH": ["116"], "CLOTHING_FIT": ["классический"], "COLORS": ["прозрачный"]}},
  {"query": "новинка товар", "attributes": {}},
  {"query": "вес 250г", "attributes": {"WEIGHT": ["250г"]}},
  {"query": "детская обувь 24 мужской lacoste", "attributes": {"BRANDS": ["lacoste"], "SHOE_SIZES_KIDS": ["24"]}},
  {"query": "36 размер ноги", "attributes": {"SHOE_SIZES_ADULT": ["36"]}},
  {"query": "XL размер", "attributes": {"CLOTHING_SIZES_LETTER": ["XL"]}},
  {"query": "зарядка детская", "attributes": {"CATEGORIES": ["зарядка"]}},
  {"query": "джинсы классический", "attributes": {"CLOTHING_FIT": ["классический"]}},
  {"query": "бордовый цвет", "attributes": {"COLORS": ["бордовый"]}},
  {"query": "распродажа объем 1л", "attributes": {"CLOTHING_FIT": ["зауженный"], "ELECTRONICS_MEMORY": ["4гб"], "VOLUME": ["1л"]}},
  {"query": "одежда 56", "attributes": {"CLOTHING_SIZES_NUMERIC": ["56"]}},
  {"query": "товар красный", "attributes": {"COLORS": ["красный"]}},
  {"query": "контейнер 500мл", "attributes": {"VOLUME": ["500мл"]}},
  {"query": "продукт 750г", "attributes": {"WEIGHT": ["750г"]}},
  {"query": "код 445566 заказ", "attributes": {}},
  {"query": "одежда на рост 62", "attributes": {"CLOTHING_KIDS_GROTH": ["62"]}},
  {"query": "размер 180х200см", "attributes": {"TEXTILE_DIMS": ["180х200см"]}},
  {"query": "gucci рост 110", "attributes": {"CLOTHING_KIDS_GROTH": ["110"], "MATERIALS": ["флис"], "BRANDS": ["gucci"], "SCREEN_DIAGONALS": ["24дюйма"]}},
  {"query": "48 размер бархат", "attributes": {"CLOTHING_SIZES_LETTER": ["XXL"], "CLOTHING_SIZES_NUMERIC": ["48"], "MATERIALS": ["бархат"]}},
  {"query": "ботинки 34 детские", "attributes": {"SHOE_SIZES_KIDS": ["34"]}},
  {"query": "бирюзовый женский узкий размер XXXL", "attributes": {"COLORS": ["бирюзовый"], "CLOTHING_FIT": ["узкий"], "CLOTHING_SIZES_LETTER": ["XXXL"]}},
  {"query": "РАЗМЕР 200Х220СМ", "attributes": {"TEXTILE_DIMS": ["200х220см"]}},
  {"query": "хит заказ", "attributes": {}},
  {"query": "быстрая доставка", "attributes": {}},
  {"query": "ТОВАР 5ММ", "attributes": {"LINEAR_DIMS_CM_MM": ["5мм"]}},
  {"query": "zzzxxx заказ", "attributes": {}},
  {"query": "длина 35см", "attributes": {"LINEAR_DIMS_CM_MM": ["35см"]}},
  {"query": "размер XXXL объем 10л детский желтый", "attributes": {"VOLUME": ["10л"], "COLORS": ["желтый"], "CLOTHING_SIZES_LETTER": ["XXXL"]}},
  {"query": "111 купить", "attributes": {}},
  {"query": "10см 32гб обувь 45 женский вес 10кг", "attributes": {"LINEAR_DIMS_CM_MM": ["10см"], "WEIGHT": ["10кг"], "ELECTRONICS_MEMORY": ["32гб"], "SHOE_SIZES_ADULT": ["45"]}},
  {"query": "объем 750мл", "attributes": {"VOLUME": ["750мл"]}},
  {"query": "продукт 250г", "attributes": {"WEIGHT": ["250г"]}},
  {"query": "диагональ 6.1", "attributes": {"SCREEN_DIAGONALS": ["6.1"]}},
  {"query": "в наличии цена", "attributes": {}},
  {"query": "объем 250мл", "attributes": {"VOLUME": ["250мл"]}},
  {"query": "размер 200х200см размер S новинка 40 размер", "attributes": {"CLOTHING_SIZES_LETTER": ["S"], "CLOTHING_SIZES_NUMERIC": ["40"], "TEXTILE_DIMS": ["200х200см"]}},
  {"query": "оригинал вес 50г объем 2л slim", "attributes": {"WEIGHT": ["50г"], "VOLUME": ["2л"], "CLOTHING_FIT": ["slim"]}},
  {"query": "128 сантиметр ребенок", "attributes": {"CLOTHING_KIDS_GROTH": ["128"]}},
  {"query": "детский размер 180х200см", "attributes": {"ELECTRONICS_MEMORY": ["4гб"], "LINEAR_DIMS_CM_MM": ["1м"], "SCREEN_DIAGONALS": ["6.7"], "TEXTILE_DIMS": ["180х200см"]}},
  {"query": "РАЗМЕР XXXL", "attributes": {"CLOTHING_SIZES_LETTER": ["XXXL"]}},
  {"query": "рост 110 новинка вес 1кг", "attributes": {"CLOTHING_KIDS_GROTH": ["110"], "WEIGHT": ["1кг"]}},
  {"query": "лучшая цена заказ", "attributes": {}},
  {"query": "объем 10л купить сумка мятный", "attributes": {"CATEGORIES": ["сумка"], "COLORS": ["мятный"], "VOLUME": ["10л"]}},
  {"query": "купить рост 122 детская обувь 20", "attributes": {"SHOE_SIZES_KIDS": ["20"], "CLOTHING_SIZES_LETTER": ["M"], "CLOTHING_KIDS_GROTH": ["122"]}},
  {"query": "быстрая доставка цена", "attributes": {}},
  {"query": "детская обувь 23 объем 750мл р-р 240х260см новинка", "attributes": {"SHOE_SIZES_KIDS": ["23"], "TEXTILE_DIMS": ["240х260см"], "VOLUME": ["750мл"]}},
  {"query": "ОДЕЖДА ШЕРСТЬ", "attributes": {"MATERIALS": ["шерсть"]}},
  {"query": "купить hp объем 3л", "attributes": {"ELECTRONICS_MEMORY": ["8гб"], "BRANDS": ["hp"], "VOLUME": ["3л"], "WEIGHT": ["1кг"]}},
  {"query": "флешка мужская", "attributes": {"CATEGORIES": ["флешка"]}},
  {"query": "вес 1кг размер 70х70см женский", "attributes": {"TEXTILE_DIMS": ["70х70см"], "WEIGHT": ["1кг"]}},
  {"query": "Бутылка 500мл", "attributes": {"VOLUME": ["500мл"]}},
  {"query": "размер обуви 37", "attributes": {"SHOE_SIZES_ADULT": ["37"]}},
  {"query": "телевизор 6.1", "attributes": {"SCREEN_DIAGONALS": ["6.1"]}},
  {"query": "вискоза ткань", "attributes": {"MATERIALS": ["вискоза"]}},
  {"query": "обувь 46 купить детская обувь 33", "attributes": {"SHOE_SIZES_ADULT": ["46"], "SHOE_SIZES_KIDS": ["33"]}},
  {"query": "id 789012", "attributes": {}},
  {"query": "41 р-р ноги", "attributes": {"SHOE_SIZES_ADULT": ["41"]}},
  {"query": "кроссовки 36", "attributes": {"SHOE_SIZES_ADULT": ["36"]}},
  {"query": "ПОСАДКА REGULAR", "attributes": {"CLOTHING_FIT": ["regular"]}},
  {"query": "футболка xxl", "attributes": {"CLOTHING_SIZES_LETTER": ["XXL"]}},
  {"query": "флис купить рост 98", "attributes": {"MATERIALS": ["флис"], "CLOTHING_KIDS_GROTH": ["98"]}},
  {"query": "упаковка 250г", "attributes": {"WEIGHT": ["250г"]}},
  {"query": "купить сейчас заказ", "attributes": {}},
  {"query": "быстрая доставка товар", "attributes": {}},
  {"query": "мужской 8гб обувь 38 бархат рост 62", "attributes": {"ELECTRONICS_MEMORY": ["8гб"], "SHOE_SIZES_ADULT": ["38"], "CLOTHING_KIDS_GROTH": ["62"], "MATERIALS": ["бархат"]}},
  {"query": "20см размер сант новинка", "attributes": {"LINEAR_DIMS_CM_MM": ["20см"], "TEXTILE_DIMS": ["150х200см"]}},
  {"query": "вес 5кг", "attributes": {"WEIGHT": ["5кг"]}},
  {"query": "объем 500мл 2тб", "attributes": {"VOLUME": ["500мл"], "ELECTRONICS_MEMORY": ["2тб"], "CLOTHING_FIT": ["oversized"], "TEXTILE_DIMS": ["240х260см"]}},
  {"query": "колонка новинка рост 80 белый обувь 46", "attributes": {"SHOE_SIZES_ADULT": ["46"], "CATEGORIES": ["колонка"], "COLORS": ["белый"], "CLOTHING_KIDS_GROTH": ["80"]}},
  {"query": "свободный женский куртка 40см", "attributes": {"CLOTHING_FIT": ["свободный"], "LINEAR_DIMS_CM_MM": ["40см"], "CATEGORIES": ["куртка"]}},
  {"query": "новинка атлас вес 100г", "attributes": {"MATERIALS": ["атлас"], "WEIGHT": ["100г"]}},
  {"query": "Объем 50мл", "attributes": {"VOLUME": ["50мл"]}},
  {"query": "ФУТБОЛКА L", "attributes": {"CLOTHING_SIZES_LETTER": ["L"]}},
  {"query": "puma магазин", "attributes": {"BRANDS": ["puma"]}},
  {"query": "ботинки 26 детские", "attributes": {"SHOE_SIZES_KIDS": ["26"]}},
  {"query": "id 789012 заказ", "attributes": {}},
  {"query": "id 789012 товар", "attributes": {}},
  {"query": "Плед 200х200см", "attributes": {"TEXTILE_DIMS": ["200х200см"]}},
  {"query": "58 разммер 2м", "attributes": {"LINEAR_DIMS_CM_MM": ["2м"], "BRANDS": ["adidas"], "SHOE_SIZES_KIDS": ["30"], "CLOTHING_SIZES_NUMERIC": ["58"]}},
  {"query": "ТОВАР СИНИЙ", "attributes": {"COLORS": ["синий"]}},
  {"query": "товар бежевый", "attributes": {"COLORS": ["бежевый"]}},
  {"query": "плед сантиметр", "attributes": {"TEXTILE_DIMS": ["200х220см"]}},
  {"query": "объем 1л", "attributes": {"VOLUME": ["1л"]}},
  {"query": "разммер слим", "attributes": {"CLOTHING_SIZES_LETTER": ["M"]}},
  {"query": "бархат объем 750мл джинсы рост 110", "attributes": {"VOLUME": ["750мл"], "MATERIALS": ["бархат"], "CLOTHING_KIDS_GROTH": ["110"], "CATEGORIES": ["джинсы"]}},
  {"query": "100г товар", "attributes": {"WEIGHT": ["100г"]}},
  {"query": "код товара 555 цена", "attributes": {}},
  {"query": "32 разммер ноги детский", "attributes": {"SHOE_SIZES_KIDS": ["32"]}},
  {"query": "товар серебряный", "attributes": {"COLORS": ["серебряный"]}},
  {"query": "Полотенце 140х200см", "attributes": {"TEXTILE_DIMS": ["140х200см"]}},
  {"query": "ПЛЕД 50Х50СМ", "attributes": {"TEXTILE_DIMS": ["50х50см"]}},
  {"query": "asdfgh цена", "attributes": {}},
  {"query": "Детская обувь 27", "attributes": {"SHOE_SIZES_KIDS": ["27"]}},
  {"query": "товар прозрачный", "attributes": {"COLORS": ["прозрачный"]}},
  {"query": "нейлон мужской размер 50х50см columbia", "attributes": {"TEXTILE_DIMS": ["50х50см"], "BRANDS": ["columbia"], "MATERIALS": ["нейлон"]}},
  {"query": "детская обувь 34 рост 104 512гб", "attributes": {"CLOTHING_KIDS_GROTH": ["104"], "SHOE_SIZES_KIDS": ["34"], "ELECTRONICS_MEMORY": ["512гб"]}},
  {"query": "объем 1л р-р приталеный 1тб", "attributes": {"COLORS": ["салатовый"], "ELECTRONICS_MEMORY": ["1тб"], "VOLUME": ["1л"], "CLOTHING_SIZES_LETTER": ["M"]}},
  {"query": "qwerty123 акция", "attributes": {}},
  {"query": "толстовка эластан экран 5дюймов распродажа", "attributes": {"SCREEN_DIAGONALS": ["5дюймов"], "MATERIALS": ["эластан"], "CATEGORIES": ["толстовка"]}},
  {"query": "ПРОДУКТ 1.5КГ", "attributes": {"WEIGHT": ["1.5кг"]}},
  {"query": "плед сантиметр", "attributes": {"TEXTILE_DIMS": ["150х200см"]}},
  {"query": "код товара 555", "attributes": {}},
  {"query": "Apple оригинал", "attributes": {"BRANDS": ["apple"]}},
  {"query": "новинка цена", "attributes": {}},
  {"query": "детский обувь 41", "attributes": {"SHOE_SIZES_ADULT": ["41"], "LINEAR_DIMS_CM_MM": ["40см"]}},
  {"query": "test купить", "attributes": {}},
  {"query": "объем 2л новинка обувь 38", "attributes": {"VOLUME": ["2л"], "SHOE_SIZES_ADULT": ["38"]}},
  {"query": "Плед 140х200см", "attributes": {"TEXTILE_DIMS": ["140х200см"]}},
  {"query": "новинка экран 50дюймов", "attributes": {"CLOTHING_FIT": ["зауженный"], "SCREEN_DIAGONALS": ["50дюймов"]}},
  {"query": "одежда вискоза", "attributes": {"MATERIALS": ["вискоза"]}},
  {"query": "the north face распродажа", "attributes": {"BRANDS": ["the north face"]}},
  {"query": "M размер", "attributes": {"CLOTHING_SIZES_LETTER": ["M"]}},
  {"query": "Фирменный calvin klein", "attributes": {"BRANDS": ["calvin klein"]}},
  {"query": "одежда на рост 110", "attributes": {"CLOTHING_KIDS_GROTH": ["110"]}},
  {"query": "мужской широкий размер L 58 размер", "attributes": {"CLOTHING_SIZES_LETTER": ["L"], "CLOTHING_SIZES_NUMERIC": ["58"], "CLOTHING_FIT": ["широкий"]}},
  {"query": "sku 98765", "attributes": {}},
  {"query": "вес 2кг", "attributes": {"WEIGHT": ["2кг"]}},
  {"query": "длина 10мм", "attributes": {"LINEAR_DIMS_CM_MM": ["10мм"]}},
  {"query": "ЗАУЖЕННЫЙ КРОЙ", "attributes": {"CLOTHING_FIT": ["зауженный"]}},
  {"query": "память 512гб", "attributes": {"ELECTRONICS_MEMORY": ["512гб"]}},
  {"query": "шелк вес 750г детская обувь 26", "attributes": {"TEXTILE_DIMS": ["140х200см"], "SHOE_SIZES_KIDS": ["26"], "MATERIALS": ["шелк"], "WEIGHT": ["750г"]}},
  {"query": "кроссовки 36", "attributes": {"SHOE_SIZES_ADULT": ["36"]}},
  {"query": "оригинал размер сантиметр размер XXL штора объем 50мл", "attributes": {"CLOTHING_SIZES_LETTER": ["XXL"], "VOLUME": ["50мл"], "TEXTILE_DIMS": ["50х50см"], "CATEGORIES": ["штора"]}},
  {"query": "контейнер 10л", "attributes": {"VOLUME": ["10л"]}},
  {"query": "5мм levis", "attributes": {"LINEAR_DIMS_CM_MM": ["5мм"], "TEXTILE_DIMS": ["160х200см"], "BRANDS": ["levis"]}},
  {"query": "продукт кг", "attributes": {"WEIGHT": ["5кг"]}},
  {"query": "рост 68 детская обувь 32 сант новинка", "attributes": {"SHOE_SIZES_KIDS": ["32"], "CLOTHING_KIDS_GROTH": ["68"], "LINEAR_DIMS_CM_MM": ["100см"]}},
  {"query": "10мм оригинал детская обувь 34", "attributes": {"LINEAR_DIMS_CM_MM": ["10мм"], "SHOE_SIZES_KIDS": ["34"]}},
  {"query": "вес 250г женский размер XS calvin klein объем", "attributes": {"VOLUME": ["1л"], "BRANDS": ["calvin klein"], "WEIGHT": ["250г"], "CLOTHING_SIZES_LETTER": ["XS"]}},
  {"query": "код товара 555 товар", "attributes": {}},
  {"query": "объем 2л мужской гигабайт", "attributes": {"ELECTRONICS_MEMORY": ["8гб"], "VOLUME": ["2л"]}},
  {"query": "БОТИНКИ 32 ДЕТСКИЕ", "attributes": {"SHOE_SIZES_KIDS": ["32"]}},
  {"query": "телевизор 6.7", "attributes": {"SCREEN_DIAGONALS": ["6.7"]}},
  {"query": "мужской размер L 1тб", "attributes": {"CLOTHING_SIZES_LETTER": ["L"], "ELECTRONICS_MEMORY": ["1тб"]}},
  {"query": "распродажа цена", "attributes": {}},
  {"query": "одежда полиэстер", "attributes": {"MATERIALS": ["полиэстер"]}},
  {"query": "детская обувь 31 мужской замша", "attributes": {"MATERIALS": ["замша"], "SHOE_SIZES_KIDS": ["31"]}},
  {"query": "tommy hilfiger размер 50х50см шелк", "attributes": {"BRANDS": ["tommy hilfiger"], "MATERIALS": ["шелк"], "TEXTILE_DIMS": ["50х50см"]}},
  {"query": "РАЗМЕР 44", "attributes": {"CLOTHING_SIZES_NUMERIC": ["44"]}},
  {"query": "одежда slimfit", "attributes": {"CLOTHING_SIZES_LETTER": ["M"]}},
  {"query": "рост 74", "attributes": {"CLOTHING_KIDS_GROTH": ["74"]}},
  {"query": "zzzxxx товар", "attributes": {}},
  {"query": "нейлон купить", "attributes": {"ELECTRONICS_MEMORY": ["256гб"], "MATERIALS": ["нейлон"]}},
  {"query": "код 445566 товар", "attributes": {}},
  {"query": "купить свитер", "attributes": {"CATEGORIES": ["свитер"]}},
  {"query": "В цвете серый", "attributes": {"COLORS": ["серый"]}},
  {"query": "32гб рам детский", "attributes": {"ELECTRONICS_MEMORY": ["32гб рам"], "LINEAR_DIMS_CM_MM": ["35см"]}},
  {"query": "детская обувь 25 экран 6.1 эластан", "attributes": {"COLORS": ["хаки"], "MATERIALS": ["эластан"], "SCREEN_DIAGONALS": ["6.1"], "SHOE_SIZES_KIDS": ["25"]}},
  {"query": "asus распродажа", "attributes": {"BRANDS": ["asus"]}},
  {"query": "экран дюйм р-р см детский", "attributes": {"CLOTHING_KIDS_GROTH": ["62"], "TEXTILE_DIMS": ["200х200см"], "SCREEN_DIAGONALS": ["40дюймов"]}},
  {"query": "подушка размер XXL объем 3л приталенный", "attributes": {"CLOTHING_FIT": ["приталенный"], "VOLUME": ["3л"], "CATEGORIES": ["подушка"], "CLOTHING_SIZES_LETTER": ["XXL"]}},
  {"query": "футболка xxxl", "attributes": {"CLOTHING_SIZES_LETTER": ["XXXL"]}},
  {"query": "детское 80", "attributes": {"CLOTHING_KIDS_GROTH": ["80"]}}
]